choixe/__init__.py
choixe/bulletins.py
choixe/choixe.py
choixe/configurations.py
choixe/directives.py
choixe/importers.py
choixe/inquirer.py
choixe/placeholders.py
choixe/spooks.py
choixe/sweepers.py
choixe/cli/__init__.py
choixe/cli/check.py
choixe/cli/compile.py
choixe/cli/main.py
choixe-0.1.11.dist-info/LICENSE
choixe-0.1.11.dist-info/METADATA
choixe-0.1.11.dist-info/WHEEL
choixe-0.1.11.dist-info/entry_points.txt
choixe-0.1.11.dist-info/top_level.txt
choixe-0.1.11.dist-info/RECORD
