Metadata-Version: 2.1
Name: choixe
Version: 0.1.11
Summary: Configurations Superpowers
Home-page: https://github.com/eyecan-ai/choixe
Author: daniele de gregorio
Author-email: daniele.degregorio@eyecan.ai
License: GNU General Public License v3
Keywords: choixe
Platform: UNKNOWN
Classifier: Development Status :: 2 - Pre-Alpha
Classifier: Intended Audience :: Developers
Classifier: License :: OSI Approved :: GNU General Public License v3 (GPLv3)
Classifier: Natural Language :: English
Classifier: Programming Language :: Python :: 3
Classifier: Programming Language :: Python :: 3.5
Classifier: Programming Language :: Python :: 3.6
Classifier: Programming Language :: Python :: 3.7
Classifier: Programming Language :: Python :: 3.8
Requires-Python: >=3.5
License-File: LICENSE
Requires-Dist: click (>=7.1.2)
Requires-Dist: rich
Requires-Dist: python-box (>=5.2.0)
Requires-Dist: numpy
Requires-Dist: deepdiff (>=5.2.2)
Requires-Dist: schema (>=0.7.4)
Requires-Dist: pydash (>=4.9.2)
Requires-Dist: PyYAML
Requires-Dist: toml (>=0.10.2)
Requires-Dist: pika
Requires-Dist: inquirer
